mergekit/__init__.py
mergekit/architecture.py
mergekit/card.py
mergekit/common.py
mergekit/config.py
mergekit/graph.py
mergekit/merge.py
mergekit/options.py
mergekit/plan.py
mergekit/sparsify.py
mergekit/_data/__init__.py
mergekit/_data/architectures/__init__.py
mergekit/_data/architectures/baichuan.json
mergekit/_data/architectures/bert-masked-lm.json
mergekit/_data/architectures/bert-sequence-classification.json
mergekit/_data/architectures/bert.json
mergekit/_data/architectures/chatglm.json
mergekit/_data/architectures/cohere.json
mergekit/_data/architectures/distilbert-masked-lm.json
mergekit/_data/architectures/distilbert-sequence-classification.json
mergekit/_data/architectures/distilbert-token-classification.json
mergekit/_data/architectures/distilbert.json
mergekit/_data/architectures/exaone.json
mergekit/_data/architectures/falcon.json
mergekit/_data/architectures/gemma.json
mergekit/_data/architectures/gemma2.json
mergekit/_data/architectures/gpt-neox.json
mergekit/_data/architectures/gpt2-sequence-classification.json
mergekit/_data/architectures/gpt2.json
mergekit/_data/architectures/gptbigcode.json
mergekit/_data/architectures/internlm2.json
mergekit/_data/architectures/jais.json
mergekit/_data/architectures/llama.json
mergekit/_data/architectures/mamba.json
mergekit/_data/architectures/mistral.json
mergekit/_data/architectures/phi-1.json
mergekit/_data/architectures/phi2-old.json
mergekit/_data/architectures/phi2.json
mergekit/_data/architectures/phi3-small.json
mergekit/_data/architectures/phi3.json
mergekit/_data/architectures/qwen.json
mergekit/_data/architectures/qwen2.json
mergekit/_data/architectures/roberta-masked-lm.json
mergekit/_data/architectures/roberta-sequence-classification.json
mergekit/_data/architectures/roberta-token-classification.json
mergekit/_data/architectures/roberta.json
mergekit/_data/architectures/solar.json
mergekit/_data/architectures/stablelm.json
mergekit/_data/architectures/stablelm2.json
mergekit-0.0.5.1.dist-info/LICENSE
mergekit-0.0.5.1.dist-info/METADATA
mergekit-0.0.5.1.dist-info/WHEEL
mergekit-0.0.5.1.dist-info/entry_points.txt
mergekit-0.0.5.1.dist-info/top_level.txt
mergekit-0.0.5.1.dist-info/RECORD
