Metadata-Version: 2.1
Name: mergekit
Version: 0.0.5.1
Summary: Tools for merging pre-trained large language models
Author-email: Charles Goddard <chargoddard@gmail.com>
License: LGPL-3.0-or-later
Project-URL: repository, https://github.com/cg123/mergekit
License-File: LICENSE
Requires-Dist: torch >=2.0.0
Requires-Dist: tqdm ==4.66.5
Requires-Dist: click ==8.1.7
Requires-Dist: safetensors ~=0.4.3
Requires-Dist: accelerate ~=1.0.1
Requires-Dist: pydantic ~=2.9.2
Requires-Dist: immutables ==0.20
Requires-Dist: transformers >=4.45.2
Requires-Dist: tokenizers >=0.20.1
Requires-Dist: huggingface-hub
Requires-Dist: peft
Requires-Dist: typing-extensions
Requires-Dist: sentencepiece
Requires-Dist: protobuf
Requires-Dist: scipy
Requires-Dist: datasets
Provides-Extra: dev
Requires-Dist: black ~=24.10.0 ; extra == 'dev'
Requires-Dist: isort ~=5.13.2 ; extra == 'dev'
Requires-Dist: pre-commit ~=4.0.1 ; extra == 'dev'
Provides-Extra: evolve
Requires-Dist: ray ; extra == 'evolve'
Requires-Dist: cma ; extra == 'evolve'
Requires-Dist: lm-eval ; extra == 'evolve'
Requires-Dist: wandb ; extra == 'evolve'
Provides-Extra: test
Requires-Dist: pytest ~=8.3.3 ; extra == 'test'
Provides-Extra: vllm
Requires-Dist: vllm ==0.3.2 ; extra == 'vllm'
Requires-Dist: lm-eval[vllm] ; extra == 'vllm'
